{
    "volumenes_tablas":  {
                             "estancias_hosp":  {
                                                    "SIGESAPOL":  1280,
                                                    "CPT":  674
                                                },
                             "bdt_emergencia":  {
                                                    "SIGESAPOL":  15319,
                                                    "CPT":  51684
                                                },
                             "bdt_consulta":  {
                                                  "SIGESAPOL":  260994,
                                                  "CPT":  2426
                                              },
                             "lab_hospitalizacion":  {
                                                         "SIGESAPOL":  794,
                                                         "CPT":  56968
                                                     },
                             "lab_consulta":  {
                                                  "SIGESAPOL":  12995,
                                                  "CPT":  71790
                                              },
                             "lab_emergencia":  {
                                                    "SIGESAPOL":  16046,
                                                    "CPT":  120293
                                                },
                             "bdt_hospitalizacion":  {
                                                         "SIGESAPOL":  10739,
                                                         "CPT":  77815
                                                     }
                         },
    "observaciones":  {
                          "medico_distinto":  271,
                          "transiciones":  731,
                          "duplicados_origen":  407,
                          "cantidad_distinta":  0,
                          "cpms_derivado_hospitalizacion":  1286,
                          "cpms_derivado_emergencia":  1841
                      },
    "deduplicacion":  {
                          "duplicados_ciertos":  310,
                          "monto_evitado_doble_cobro":  12335.670000000006
                      },
    "fuente_canonica":  "SIGESAPOL",
    "periodo":  "2025-10",
    "volumenes_tramas":  {
                             "trama_farmacia":  118987,
                             "trama_consulta_externa":  348341,
                             "trama_hospitalizacion":  17456,
                             "trama_emergencia":  31953
                         },
    "tiempos_segundos":  {
                             "reclasificacion_24h":  0.11,
                             "armado_emergencia":  1.1,
                             "deduplicacion":  7.37,
                             "consolidacion":  7.52,
                             "armado_hosp":  0.73,
                             "control_integridad":  0.97,
                             "paso1c_proc":  27.43,
                             "paso2_cpt":  66.74,
                             "hermeticidad":  0.97,
                             "paso1b_hosp":  0.31,
                             "traslado_pgdump":  8.46,
                             "armado_consulta":  5.56,
                             "paso1":  1.1,
                             "armado_farmacia":  71.83
                         }
}